behindit/__init__.py
behindit/main.py
BehindIt-0.1.0.dist-info/LICENSE
BehindIt-0.1.0.dist-info/METADATA
BehindIt-0.1.0.dist-info/WHEEL
BehindIt-0.1.0.dist-info/entry_points.txt
BehindIt-0.1.0.dist-info/top_level.txt
BehindIt-0.1.0.dist-info/RECORD
