Metadata-Version: 2.1
Name: BehindIt
Version: 0.1.0
Summary: Finding out who shared an instagram or tiktok content
Author: Gobutsu
Requires-Python: >=3.6
License-File: LICENSE
Requires-Dist: requests
Requires-Dist: rich
Requires-Dist: argparse
